mcp_image_upload/__init__.py
mcp_image_upload-0.1.0.dist-info/METADATA
mcp_image_upload-0.1.0.dist-info/WHEEL
mcp_image_upload-0.1.0.dist-info/entry_points.txt
mcp_image_upload-0.1.0.dist-info/RECORD
