Metadata-Version: 2.4
Name: mcp-image-upload
Version: 0.1.0
Summary: Add your description here
Author-email: 洛水 <857762910@qq.com>
Requires-Python: >=3.13
Requires-Dist: mcp[cli]>=1.9.4
Requires-Dist: requests>=2.31.0
